<?xml version = '1.0' encoding = 'UTF-8'?>
<TableProxyOraclev11g class="oracle.dbtools.crest.model.design.storage.oracle.v11g.TableProxyOraclev11g" name="COURSE" directorySegmentName="seg_0" id="6536B230-F255-81B7-7B8B-724EE4B4813F">
<createdBy>GDJ54</createdBy>
<createdTime>2022-08-25 08:47:55 UTC</createdTime>
<ownerDesignName>이게머지</ownerDesignName>
<schemaObject>58BF9FFF-C60F-6901-26DF-0C5647CA9BD8</schemaObject>
<logging>YES</logging>
<partitionedRowMovement>DISABLE</partitionedRowMovement>
<segment>78694F5B-7DCE-A374-A85C-E0DB7F19094B</segment>
<tableSpace>68A8E0F7-BC8E-0E59-EE53-A0E13410A9CF</tableSpace>
<temporaryChanged>false</temporaryChanged>
<accessDriverType>oracle_loader</accessDriverType>
<rejectLimit></rejectLimit>
<columnProxies itemClass="oracle.dbtools.crest.model.design.storage.oracle.v12c.ColumnProxyOraclev12c">
<ColumnProxy name="COU_NAME" id="39E4AF77-3EFB-1C86-011F-56C691DF49D2">
<createdBy>GDJ54</createdBy>
<createdTime>2022-08-25 08:47:55 UTC</createdTime>
<ownerDesignName>이게머지</ownerDesignName>
</ColumnProxy>
<ColumnProxy name="COU_NO" id="3F420A89-54FF-A262-4003-28F65E83B0B7">
<createdBy>GDJ54</createdBy>
<createdTime>2022-08-25 08:47:55 UTC</createdTime>
<ownerDesignName>이게머지</ownerDesignName>
</ColumnProxy>
<ColumnProxy name="COU_COM" id="AD86DD65-5C4D-AFB2-0EE8-37DFF6F43E51">
<createdBy>GDJ54</createdBy>
<createdTime>2022-08-25 08:47:55 UTC</createdTime>
<ownerDesignName>이게머지</ownerDesignName>
</ColumnProxy>
</columnProxies>
<indexProxies>
<IndexProxy class="oracle.dbtools.crest.model.design.storage.oracle.v10g.IndexProxyOraclev10g" name="PK_COURSE" id="BDDB793A-0305-D927-3D70-8A8A73555743">
<createdBy>GDJ54</createdBy>
<createdTime>2022-08-25 08:47:55 UTC</createdTime>
<ownerDesignName>이게머지</ownerDesignName>
<schemaObject>58BF9FFF-C60F-6901-26DF-0C5647CA9BD8</schemaObject>
<segment>9CA89A04-FFF2-0CB3-B601-5439B3E91D6A</segment>
<tableSpace>68A8E0F7-BC8E-0E59-EE53-A0E13410A9CF</tableSpace>
</IndexProxy>
</indexProxies>
<primaryKeys>
<PrimaryKey class="oracle.dbtools.crest.model.design.storage.oracle.v10g.PKProxyOraclev10g" name="PK_COURSE" id="F3C8EB33-654C-6409-03B7-FB24AA4D2252">
<createdBy>GDJ54</createdBy>
<createdTime>2022-08-25 08:47:55 UTC</createdTime>
<ownerDesignName>이게머지</ownerDesignName>
<segment>9CA89A04-FFF2-0CB3-B601-5439B3E91D6A</segment>
<tableSpace>68A8E0F7-BC8E-0E59-EE53-A0E13410A9CF</tableSpace>
<existingIndex>BDDB793A-0305-D927-3D70-8A8A73555743</existingIndex>
<indexSegment>9CA89A04-FFF2-0CB3-B601-5439B3E91D6A</indexSegment>
<indexSort>SORTED</indexSort>
<usingIndex>BY INDEX NAME</usingIndex>
</PrimaryKey>
</primaryKeys>
</TableProxyOraclev11g>